{
    "question_number": "402",
    "main_question": "Which one of the following is the most populated province in Canada?",
    "question": "Which one of the following is the most populated province in Canada?",
    "possible_answers": [
        "A. Quebec",
        "B. British Columbia",
        "C. Ontario",
        "D. Alberta"
    ],
    "answer": "C. Ontario",
    "page": "402",
    "explanatory_sentence": "Ontario is the most populous province in Canada, largely because it contains Toronto and the Greater Toronto Area, the country's largest population center.",
    "correct_answer": "C"
}